Metadata-Version: 2.1
Name: base36py
Version: 0.2.0
Summary: A lightweight Python library for encoding and decoding numbers between base10 and base36.
Home-page: https://github.com/DanishjeetSingh/base36py
Author: Danishjeet Singh
Author-email: danishjeetsingh@gmail.com
Classifier: Programming Language :: Python :: 3
Classifier: License :: OSI Approved :: MIT License
Classifier: Operating System :: OS Independent
Requires-Python: >=3.6
License-File: LICENSE
